txtstorage/__init__.py
txtstorage/timetrack.py
txtstorage-0.1.0.dist-info/METADATA
txtstorage-0.1.0.dist-info/WHEEL
txtstorage-0.1.0.dist-info/top_level.txt
txtstorage-0.1.0.dist-info/RECORD
