Metadata-Version: 2.1
Name: txtstorage
Version: 0.1.0
Summary: silly silly sily suilly isilly silly
Home-page: https://github.com/yourusername/timetrack
Author: Logan Harper
Author-email: negro@gmail.com
Classifier: Programming Language :: Python :: 3
Classifier: License :: OSI Approved :: MIT License
Classifier: Operating System :: OS Independent
Requires-Python: >=3.6
Requires-Dist: requests
